pycertainties/__init__.py
pycertainties/calculations.py
pycertainties/pprinting.py
pycertainties/strings.py
pycertainties/utilities.py
pycertainties/val.py
pycertainties-1.0.2.dist-info/METADATA
pycertainties-1.0.2.dist-info/WHEEL
pycertainties-1.0.2.dist-info/license.txt
pycertainties-1.0.2.dist-info/top_level.txt
pycertainties-1.0.2.dist-info/RECORD
