Metadata-Version: 2.1
Name: pycertainties
Version: 1.0.2
Summary: Module providing utilities for working with values with uncertainties
Home-page: https://github.com/larashores
Author: Lara Shores
Author-email: lara.shores@outlook.com
License: UNKNOWN
Platform: UNKNOWN
Classifier: Intended Audience :: Science/Research
Classifier: License :: OSI Approved :: MIT License
Classifier: Programming Language :: Python :: 3
Classifier: Topic :: Scientific/Engineering
Requires-Python: >=3.8
Requires-Dist: sympy
Requires-Dist: numpy
